minecraftcraftscraping.py
minecraftcraftscraping-0.0.1.dist-info/LICENSE.txt
minecraftcraftscraping-0.0.1.dist-info/METADATA
minecraftcraftscraping-0.0.1.dist-info/WHEEL
minecraftcraftscraping-0.0.1.dist-info/top_level.txt
minecraftcraftscraping-0.0.1.dist-info/RECORD
